toggl_to_redmine_core/__init__.py
toggl_to_redmine_core/config.py
toggl_to_redmine_core/exceptions.py
toggl_to_redmine_core/redmine_integrator.py
toggl_to_redmine_core/time_entry.py
toggl_to_redmine_core/toggl_integrator.py
toggl_to_redmine_core/toggl_to_redmine.py
toggl_to_redmine_core-1.3.3.dist-info/METADATA
toggl_to_redmine_core-1.3.3.dist-info/WHEEL
toggl_to_redmine_core-1.3.3.dist-info/top_level.txt
toggl_to_redmine_core-1.3.3.dist-info/RECORD
