Metadata-Version: 2.1
Name: toggl-to-redmine-core
Version: 1.3.3
Summary: Core package for the toggl_to_redmine import tool
Home-page: https://github.com/eduardocanellas/toggl-to-redmine-core
Author: Eduardo Canellas
Author-email: eduardocanellas@id.uff.br
License: UNKNOWN
Platform: UNKNOWN
Classifier: Programming Language :: Python :: 3
Classifier: License :: OSI Approved :: MIT License
Classifier: Operating System :: OS Independent
Requires-Python: >=3.6
